sodas/__init__.py
sodas/analyticops/__init__.py
sodas/analyticops/environment_instance.py
sodas/analyticops/storage/__init__.py
sodas/analyticops/storage/minio.py
sodas/authnz/__init__.py
sodas/authnz/authentication/__init__.py
sodas/authnz/authentication/user.py
sodas/datalake/__init__.py
sodas/datalake/object_storage.py
sodas/devtools/__init__.py
sodas/devtools/datalake/__init__.py
sodas/devtools/datalake/credential.py
sodas/devtools/datalake/object_storage.py
sodas/devtools/distribution/__init__.py
sodas/devtools/distribution/dataset.py
sodas/devtools/distribution/distribution.py
sodas/devtools/gateway/__init__.py
sodas/devtools/gateway/auth.py
sodas/profile/__init__.py
sodas/profile/data/__init__.py
sodas/profile/data/distribution.py
sodas-0.2.4.dist-info/METADATA
sodas-0.2.4.dist-info/WHEEL
sodas-0.2.4.dist-info/top_level.txt
sodas-0.2.4.dist-info/RECORD
