Metadata-Version: 2.1
Name: sodas
Version: 0.2.4
Summary: Sodas Workflow Development Tools
Home-page: UNKNOWN
Author: ETRI SODAS+
Author-email: siwoonson@etri.re.kr
License: UNKNOWN
Platform: UNKNOWN
Requires-Dist: boto3 ==1.26.45
Requires-Dist: pandas
Requires-Dist: requests
Requires-Dist: python-dotenv
